odoo/addons/mail_activity_plan/README.rst
odoo/addons/mail_activity_plan/__init__.py
odoo/addons/mail_activity_plan/__manifest__.py
odoo/addons/mail_activity_plan/demo/mail_activity_plan_demo.xml
odoo/addons/mail_activity_plan/i18n/es.po
odoo/addons/mail_activity_plan/i18n/it.po
odoo/addons/mail_activity_plan/i18n/mail_activity_plan.pot
odoo/addons/mail_activity_plan/models/__init__.py
odoo/addons/mail_activity_plan/models/mail_activity_plan.py
odoo/addons/mail_activity_plan/readme/CONFIGURE.rst
odoo/addons/mail_activity_plan/readme/CONTRIBUTORS.rst
odoo/addons/mail_activity_plan/readme/DESCRIPTION.rst
odoo/addons/mail_activity_plan/readme/USAGE.rst
odoo/addons/mail_activity_plan/security/ir.model.access.csv
odoo/addons/mail_activity_plan/security/security.xml
odoo/addons/mail_activity_plan/static/description/icon.png
odoo/addons/mail_activity_plan/static/description/index.html
odoo/addons/mail_activity_plan/static/src/js/mail_activity_plan.esm.js
odoo/addons/mail_activity_plan/tests/__init__.py
odoo/addons/mail_activity_plan/tests/test_mail_activity_plan.py
odoo/addons/mail_activity_plan/views/mail_activity_plan_views.xml
odoo/addons/mail_activity_plan/wizards/__init__.py
odoo/addons/mail_activity_plan/wizards/wizard_mail_activity_plan.py
odoo/addons/mail_activity_plan/wizards/wizard_mail_activity_views.xml
odoo_addon_mail_activity_plan-16.0.1.0.1.3.dist-info/METADATA
odoo_addon_mail_activity_plan-16.0.1.0.1.3.dist-info/WHEEL
odoo_addon_mail_activity_plan-16.0.1.0.1.3.dist-info/top_level.txt
odoo_addon_mail_activity_plan-16.0.1.0.1.3.dist-info/RECORD
